aistats/__init__.py
aistats/licome.py
aistats-0.0.1.dist-info/licenses/LICENSE
aistats-0.0.1.dist-info/METADATA
aistats-0.0.1.dist-info/WHEEL
aistats-0.0.1.dist-info/top_level.txt
aistats-0.0.1.dist-info/RECORD
